python_places-0.3.dist-info/METADATA
python_places-0.3.dist-info/RECORD
python_places-0.3.dist-info/WHEEL
python_places-0.3.dist-info/top_level.txt
pythonplaces/__init__.py
