Metadata-Version: 2.1
Name: python-places
Version: 0.3
Summary: A set of classes used for interacting with the Google Places API
Home-page: https://github.com/alexbotello/python-places
Author: Alexander J. Botello
Author-email: alexander.botello@g.austincc.edu
License: MIT
Platform: UNKNOWN
Requires-Dist: requests
